{
    "method": "GET",
    "headers": {
        "Server": "nginx",
        "Date": "Thu, 26 Oct 2023 05:31:57 GMT",
        "Content-Type": "text/html; charset=UTF-8",
        "Transfer-Encoding": "chunked",
        "Connection": "close",
        "Vary": "Accept-Encoding",
        "Set-Cookie": "PageLang=zh-tw; path=/; secure; HttpOnly, PageLang=zh-tw; path=/; secure; HttpOnly, _counter=48528098; path=/; secure; HttpOnly, PageLang=zh-tw; path=/; secure; HttpOnly, PageLang=zh-tw; path=/; secure; HttpOnly, PageLang=zh-tw; path=/; secure; HttpOnly, PageLang=zh-tw; path=/; secure; HttpOnly, SERVERID=; Expires=Thu, 01-Jan-1970 00:00:01 GMT; path=/; HttpOnly; Secure",
        "X-Frame-Options": "SAMEORIGIN",
        "Content-Encoding": "gzip",
        "Strict-Transport-Security": "max-age=16000000;includeSubDomains;preload",
        "Cache-control": "private"
    },
    "status_code": 200,
    "encoding": "UTF-8",
    "request_url": "https://www.nkust.edu.tw/",
    "final_url": "https://www.nkust.edu.tw/",
    "content": "<!DOCTYPE html>\n<html lang=\"zh-tw\">\n<head>\n\n\n<meta http-equiv=\"Content-Type\" content=\"text/html; charset=utf-8\">\n<meta http-equiv=\"X-UA-Compatible\" content=\"IE=edge,chrome=1\" />\n<meta name=\"viewport\" content=\"initial-scale=1.0, user-scalable=1, minimum-scale=1.0, maximum-scale=3.0\">\n<meta name=\"apple-mobile-web-app-capable\" content=\"yes\">\n<meta name=\"apple-mobile-web-app-status-bar-style\" content=\"black\">\n<meta name=\"keywords\" content=\"國立高雄科技大學,NKUST,National Kaohsiung University of Science and Technology,高科大\" />\n<meta name=\"description\" content=\"國立高雄科技大學（英語譯名：National Kaohsiung University of Science and Technology），簡稱高雄科大、高科大、高科 、NKUST。 是一所位於高雄市的國立科技大學，為臺灣學生人數規模第二大的國立大學，僅次於國立臺灣大學。由國立高雄第一科技大學、國立高雄海洋科技大學、國立高雄應用科技大學三校於2018年合併新設而成。三校資源整合以「創新創業」、「海洋科技」、「親產優質」為發展主軸。根據URAP世界大學排名2018-2019年全國科大排名第三，僅次於臺灣科大、臺北科大，南部科大排名第一，高雄科大也受教育部高等教育深耕計畫每年經費所補助全國科大排名第一。\" />\n<!-- Global site tag (gtag.js) - Google Analytics -->\n<script async src=\"https://www.googletagmanager.com/gtag/js?id=UA-142388825-3\"></script>\n<script>\n  window.dataLayer = window.dataLayer || [];\n  function gtag(){dataLayer.push(arguments);}\n  gtag('js', new Date());\n\n  gtag('config', 'UA-142388825-3');\n</script>\n\n<script type=\"application/javascript\">(function(w,d,t,r,u){w[u]=w[u]||[];w[u].push({'projectId':'10000','properties':{'pixelId':'10070464'}});var s=d.createElement(t);s.src=r;s.async=true;s.onload=s.onreadystatechange=function(){var y,rs=this.readyState,c=w[u];if(rs&&rs!=\"complete\"&&rs!=\"loaded\"){return}try{y=YAHOO.ywa.I13N.fireBeacon;w[u]=[];w[u].push=function(p){y([p])};y(c)}catch(e){}};var scr=d.getElementsByTagName(t)[0],par=scr.parentNode;par.insertBefore(s,scr)})(window,document,\"script\",\"https://s.yimg.com/wi/ytc.js\",\"dotq\");</script>\n\n\n<title>國立高雄科技大學  - 國立高雄科技大學,NKUST,National Kaohsiung University of Science and Technology</title>\n\n<link rel=\"shortcut icon\" href=\"/var/file/0/1000/msys_1000_5641621_64001.ico\" type=\"image/x-icon\" />\n<link rel=\"icon\" href=\"/var/file/0/1000/msys_1000_5641621_64001.ico\" type=\"image/x-icon\" />\n<link rel=\"bookmark\" href=\"/var/file/0/1000/msys_1000_5641621_64001.ico\" type=\"image/x-icon\" />\n\n<link rel=\"apple-touch-icon-precomposed\" href=\"/var/file/0/1000/msys_1000_5641621_64001.ico\">\n\n<link rel=\"stylesheet\" href=\"/var/file/0/1000/mobilestyle/combine-zh-tw.css?t=1680848120\" type=\"text/css\" />\n<script language=\"javascript\"><!--\n var isHome = true \n --></script>\n<script language=\"javascript\"><!--\n var isExpanMenu = false \n --></script>\n<script type=\"text/javascript\" src=\"/var/file/js/m_20230407.js\" ></script>\n</head>\n \n<body class=\"page_mobilehome webfree webw3c\">\n\n<div class=\"wrap\">\n\n\n<a href=\"#start-C\" class=\"focusable\" title=\"跳到主要內容區\">跳到主要內容區</a>\n\n\n<div class=\"fpbgvideo\"></div>\n<div class=\"minner\">\n\n<div id=\"Dyn_head\">\n<div class=\"header\">\n\t<div class=\"minner \">\n\n\n\n\n\n\n\n\t\n<div class=\"selfhead\">\n\t\t<div class=\"meditor\">\n\t\n      \n      <div class=\"header_02\"><!--第一行-->\n<div class=\"top_first\">\n<div class=\"top_first_main container\">\n<ul class=\"topnav1\">\n\t<li><a accesskey=\"U\" href=\"#U\" id=\"AU\" name=\"U\" title=\"上方內容區塊\">:::</a></li>\n\t<!--<li><a href=\"#\">回首頁</a>|</li>-->\n\t<li><a href=\"/p/17-1000.php\" title=\"網站導覽\">網站導覽</a>|</li>\n\t<li><a href=\"https://webap0.nkust.edu.tw/nkust/\" target=\"_blank\" title=\"校務系統(另開新視窗)\">校務系統</a>|</li>\n\t<li><a href=\"https://www.lib.nkust.edu.tw/portal/\" target=\"_blank\" title=\"圖書館(另開新視窗)\">圖書館</a>|</li>\n\t<!--<li><a href=\"#\">校務暨財務公開資訊</a>|</li>-->\n\t<li><a href=\"/p/404-1000-4177.php\" title=\"連絡我們\">聯絡我們</a>|</li>\n\t<li><a href=\"https://secretary.nkust.edu.tw/p/412-1002-135.php?Lang=zh-tw\" target=\"_blank\" title=\"電子報(另開新視窗)\">電子報</a>|</li>\n\t<li><a href=\"https://news.nkust.edu.tw\" title=\"公告網站\">公告網站</a>|</li>\n\t<li><a href=\"https://www.nkust.edu.tw/p/404-1000-4622.php\" title=\"行事曆\">行事曆</a>|</li>\n\t<li><a href=\"https://go.nkust.edu.tw/\" target=\"_blank\" title=\"國立高雄科技大學Mail(另開新視窗)\">Mail</a>|</li>\n\t<!--<li><a href=\"/p/404-1000-4615.php\" title=\"舊網頁\">舊網頁</a>|</li>-->\n\t<li><a href=\"https://eng.nkust.edu.tw\" target=\"_blank\" title=\"ENGLISH(另開新視窗)\">ENGLISH</a></li>\n</ul>\n</div>\n</div>\n<!--第二行-->\n\n<div class=\"top_second container\">\n<div class=\"logo\">\n<h1 style=\"margin:0;\"><a href=\"/index.php\" title=\"國立高雄科技大學\"><img alt=\"國立高雄科技大學 校徽 LOGO\" height=\"\" src=\"/var/file/0/1000/img/513/182513897.png\" width=\"400\" /> </a></h1>\n</div>\n<!--搜索phone-->\n\n<div class=\"search_phone\"><a aria-controls=\"collapseExample\" aria-expanded=\"false\" class=\"btn btn-primary navbar-toggle1\" data-toggle=\"collapse\" href=\"#collapseExample\" role=\"button\">搜索 </a>\n\n<div class=\"collapse\" id=\"collapseExample\">\n<div class=\"well\">\n<div id=\"hd_search\">&nbsp;</div>\n</div>\n</div>\n</div>\n</div>\n<!--第三行-->\n\n<div class=\"top_third\">\n<div class=\"top_third_main container\">\n<div class=\"mycollapse\"><button class=\"navbar-toggle\" data-target=\".nav-toggle\" data-toggle=\"collapse\" type=\"button\"><span class=\"glyphicons show_lines\">Menu</span></button>\n\n<div class=\"navbar-collapse collapse nav-toggle\" id=\"collapseExample2\">\n<div class=\"well\">\n<ul class=\"topnav2\">\n\t<li><a href=\"https://www.nkust.edu.tw/p/405-1000-46616,c7048.php\" title=\"未來學生\">未來學生</a>|</li>\n\t<li><a href=\"https://www.nkust.edu.tw/p/405-1000-45113,c7048.php\" title=\"在學學生\">在學學生</a>|</li>\n\t<li><a href=\"https://www.nkust.edu.tw/p/405-1000-45747,c7048.php\" target=\"_blank\" title=\"國際生(International Students)\">國際生(International Students)</a>|</li>\n\t<li><a href=\"https://www.nkust.edu.tw/p/404-1000-62954.php\" title=\"教師\">教師</a>|</li>\n\t<li><a href=\"https://www.nkust.edu.tw/p/405-1000-45314,c7048.php\" title=\"職員\">職員</a>|</li>\n\t<li><a href=\"https://www.nkust.edu.tw/p/405-1000-45727,c7048.php\" title=\"校友\">校友</a>|</li>\n\t<li><a href=\"https://www.nkust.edu.tw/p/405-1000-45749,c7048.php\" title=\"訪客\">訪客</a>|</li>\n</ul>\n\n   \n\n\n\n\n\n\n<div class=\"mnavbar mn-collapse\">\n\t<button type=\"button\" class=\"navbar-toggle\" data-toggle=\"collapse\" data-target=\".nav-toggle\">\n\t\t<span class=\"glyphicons show_lines\">Menu</span>\n\t</button>\n\t<div class=\"nav-toggle collapse navbar-collapse iosScrollToggle\">\n\t\t<div class=\"hdmenu\">\n\t\t\t<ul class=\"nav navbar-nav\" id=\"aa83149d40f78240a51c1b2ed95aa4c18_MenuTop\">\n\t\t\t\n\t\t\t\t<li   id=\"Hln_343\" class=\"dropdown\"><a class=\"dropdown-toggle\" data-toggle=\"dropdown\" href=\"/p/412-1000-82.php?Lang=zh-tw\" title=\"關於我們\">關於我們</a><ul class=\"dropdown-menu\"><li  id=\"Hln_1332\"><a href=\"https://www.nkust.edu.tw/p/412-1000-617.php\" title=\"高科大簡介\">高科大簡介</a></li><li  id=\"Hln_1334\"><a href=\"https://www.nkust.edu.tw/p/412-1000-1025.php\" title=\"高科大願景\">高科大願景</a></li><li  id=\"Hln_6068\"><a href=\"https://sdgs.nkust.edu.tw/\" target=\"_blank\"  title=\"永續承諾(另開新視窗)\">永續承諾</a></li><li  id=\"Hln_6069\"><a href=\"https://www.nkust.edu.tw/p/412-1000-1047.php\" title=\"辦學績效\">辦學績效</a></li><li  id=\"Hln_6070\"><a href=\"https://secretary.nkust.edu.tw/p/412-1002-135.php?Lang=zh-tw\" target=\"_blank\"  title=\"高科電子報(另開新視窗)\">高科電子報</a></li><li  id=\"Hln_6071\"><a href=\"https://www.nkust.edu.tw/p/412-1000-3248.php\" title=\"高科大CIS系統\">高科大CIS系統</a></li><li  id=\"Hln_6072\"><a href=\"https://rule.nkust.edu.tw/\" title=\"高科大法規彙編\">高科大法規彙編</a></li><li  id=\"Hln_6073\"><a href=\"https://public.nkust.edu.tw/\" title=\"公開資訊\">公開資訊</a></li><li  id=\"Hln_6074\"><a href=\"https://www.nkust.edu.tw/p/412-1000-2797.php\" title=\"高科校區地圖\">高科校區地圖</a></li><li  id=\"Hln_6075\"><a href=\"https://www.nkust.edu.tw/p/412-1000-5514.php\" title=\"無障礙設施導覽圖\">無障礙設施導覽圖</a></li></ul></li>\n\t\t\t\n\t\t\t\t<li   id=\"Hln_6089\" ><a  href=\"https://www.nkust.edu.tw/p/412-1000-85.php?Lang=zh-tw\" title=\"行政\">行政</a></li>\n\t\t\t\n\t\t\t\t<li   id=\"Hln_344\" ><a  href=\"/p/412-1000-4169.php\" title=\"學術\">學術</a></li>\n\t\t\t\n\t\t\t\t<li   id=\"Hln_346\" class=\"dropdown\"><a class=\"dropdown-toggle\" data-toggle=\"dropdown\" href=\"https://ada.nkust.edu.tw/\" target=\"_blank\"  title=\"招生(另開新視窗)\">招生</a><ul class=\"dropdown-menu\"><li  id=\"Hln_1644\"><a href=\"https://ada.nkust.edu.tw/\" target=\"_blank\"  title=\"招生資訊網(另開新視窗)\">招生資訊網</a></li><li  id=\"Hln_6091\"><a href=\"https://ada.nkust.edu.tw/p/412-1057-1511.php\" title=\"研究所\">研究所</a></li><li  id=\"Hln_6092\"><a href=\"https://ada.nkust.edu.tw/p/412-1057-1512.php\" title=\"日四技\">日四技</a></li><li  id=\"Hln_6093\"><a href=\"https://ada.nkust.edu.tw/p/412-1057-1560.php\" title=\"進四技\">進四技</a></li><li  id=\"Hln_6094\"><a href=\"https://ada.nkust.edu.tw/p/412-1057-1513.php\" title=\"日二技\">日二技</a></li><li  id=\"Hln_6095\"><a href=\"https://ada.nkust.edu.tw/p/412-1057-1577.php?Lang=zh-tw\" title=\"進二技\">進二技</a></li><li  id=\"Hln_6096\"><a href=\"https://ada.nkust.edu.tw/p/412-1057-1514.php\" title=\"五專\">五專</a></li><li  id=\"Hln_6097\"><a href=\"https://ada.nkust.edu.tw/p/412-1057-9240.php\" title=\"特殊專班\">特殊專班</a></li><li  id=\"Hln_6098\"><a href=\"https://ada.nkust.edu.tw/var/file/57/1057/img/1708/119813236.pdf\" target=\"_blank\"  title=\"院系所&amp;學制一覽表(另開新視窗)\">院系所&amp;學制一覽表</a></li><li  id=\"Hln_6099\"><a href=\"https://drive.google.com/file/d/1BsuZLCrsmup38qUXOtIS8RhJpft5Y9d8/view\" target=\"_blank\"  title=\"校系簡介(另開新視窗)\">校系簡介</a></li><li  id=\"Hln_1645\"><a href=\"https://cee.nkust.edu.tw/p/426-1024-3.php\" target=\"_blank\"  title=\"推教終身學習網(另開新視窗)\">推教終身學習網</a></li></ul></li>\n\t\t\t\n\t\t\t\t<li   id=\"Hln_347\" ><a  href=\"https://giving.nkust.edu.tw/\" target=\"_blank\"  title=\"捐贈興學(另開新視窗)\">捐贈興學</a></li>\n\t\t\t\n\t\t\t\t<li   id=\"Hln_4579\" class=\"dropdown\"><a class=\"dropdown-toggle\" data-toggle=\"dropdown\" href=\"javascript:void(0)\" title=\"計畫與服務\">計畫與服務</a><ul class=\"dropdown-menu\"><li  id=\"Hln_4580\"><a href=\"https://higheredu.nkust.edu.tw/\" target=\"_blank\"  title=\"高教深耕計畫(另開新視窗)\">高教深耕計畫</a></li><li  id=\"Hln_4581\"><a href=\"https://usr.nkust.edu.tw/\" target=\"_blank\"  title=\"USR計畫(另開新視窗)\">USR計畫</a></li><li  id=\"Hln_4582\"><a href=\"https://irdnew.nkust.edu.tw/\" target=\"_blank\"  title=\"研究發展處(另開新視窗)\">研究發展處</a></li><li  id=\"Hln_6077\"><a href=\"https://ord.nkust.edu.tw/\" target=\"_blank\"  title=\"產學營運處(另開新視窗)\">產學營運處</a></li><li  id=\"Hln_6078\"><a href=\"https://ord.nkust.edu.tw/p/412-1009-6268.php\" target=\"_blank\"  title=\"校級研究中心(另開新視窗)\">校級研究中心</a></li><li  id=\"Hln_6079\"><a href=\"https://iacuc.nkust.edu.tw/\" target=\"_blank\"  title=\"實驗動物照護及使用委員會(另開新視窗)\">實驗動物照護及使用委員會</a></li></ul></li>\n\t\t\t\n\t\t\t\t<li   id=\"Hln_6080\" class=\"dropdown\"><a class=\"dropdown-toggle\" data-toggle=\"dropdown\" href=\"javascript:void(0)\" title=\"專區\">專區</a><ul class=\"dropdown-menu\"><li  id=\"Hln_6081\"><a href=\"https://enterschool.nkust.edu.tw/\" target=\"_blank\"  title=\"新生專區(另開新視窗)\">新生專區</a></li><li  id=\"Hln_6082\"><a href=\"https://2019-ncov.nkust.edu.tw/\" target=\"_blank\"  title=\"防疫專區(另開新視窗)\">防疫專區</a></li><li  id=\"Hln_6090\"><a href=\"https://gender.nkust.edu.tw/\" title=\"性別平等專區\">性別平等專區</a></li></ul></li>\n\t\t\t\n\t\t\t\n\t\t\t</ul>\n\t\t</div>\n\t</div>\n</div>\n\n<script>\n$(document).ready(function(){\n\t$(\".mnavbar .navbar-toggle\").click(function(){\n\t\t$(this).toggleClass(\"open\");\n\t});\n   $('.iosScrollToggle').on('shown.bs.collapse', function () {\n\t\tvar togglePos = $(this).css('position');\n      if(togglePos !== 'static'){\n          ModalHelper.afterOpen();\n      }\n\n    });\n\n    $('.iosScrollToggle').on('hide.bs.collapse', function () {\n\t\tvar togglePos = $(this).css('position');\n      if(togglePos !== 'static'){\n\t\t\tModalHelper.beforeClose();\n      }\n\n    });\n\t\n});\n</script>\n\n\n\n\n\t\n      \n      </div>\n</div>\n</div>\n</div>\n</div>\n</div>\n\n<div id=\"banner\">&nbsp;</div>\n<script>\n$('.navbar-toggle1[href=\"#collapseExample\"]').click(function(){\n  if($('.nav-toggle').hasClass('in')){\n    $('.navbar-toggle[data-target=\".nav-toggle\"]').removeClass('open');\n    $('.nav-toggle').removeClass('in').css({'height': '1px', 'overflow':'hidden'});\n  }\n  $(this).toggleClass('open');\n});\n\n$('.navbar-toggle[data-target=\".nav-toggle\"]').click(function(){\n    if($('#collapseExample').hasClass('in')){\n        $('.navbar-toggle1[href=\"#collapseExample\"]').removeClass('open');\n        $('#collapseExample').removeClass('in').css({'height': '1px', 'overflow':'hidden'});\n    }\n    $(this).toggleClass('open');\n});\n\n$(document).ready(function(){\n     $.hajaxOpenUrl(\"/app/index.php?Action=mobileloadmod&Type=mobile_sz_mstr&Nbr=1\", '#banner');\n$.hajaxOpenUrl(\"/app/index.php?Action=mobileloadmod&Type=mobilesch&Nbr=0\",'#hd_search');\n});\n\n</script>\n   \n\t</div>\n</div>\n\n\n\n\n\t</div>\n</div>\n<script language=\"javascript\">\n\n\ttabSwitch(\"aa83149d40f78240a51c1b2ed95aa4c18_MenuTop\");\n\n\n\nif(typeof(_LoginHln)=='undefined') var _LoginHln = new hashUtil();\n\nif(typeof(_LogoutHln)=='undefined') var _LogoutHln = new hashUtil();\n\nif(typeof(_HomeHln)=='undefined') var _HomeHln = new hashUtil();\n\nif(typeof(_InternalHln)=='undefined') var _InternalHln = new hashUtil();\n\n\n$(document).ready(function(){\n   if(typeof(loginStat)=='undefined') {\n   \tif(popChkLogin()) loginStat=\"login\";\n   \telse loginStat=\"logout\";\n\t}\n\tdealHln(isHome,loginStat,$('div.hdmenu'));\n\n\t\n\t\n});\n</script>\n<noscript>本功能需使用支援JavaScript之瀏覽器才能正常操作</noscript>\n<!-- generated at Tue Oct 24 2023 16:05:00 --></div>\n\n\n<div class=\"main\">\n<div class=\"minner\">\n\n\t\n\t\n<div class=\"row col2 row_0\">\n\t<div class=\"mrow container\">\n\t\t\n\t\t\t\n\t\t\t\n\t\t\t\n\t\t\t \n\t\t\n\t\t\t\n\t\t\t\n\t\t\t\n\t\t\t\n\t\t\t\t\n        \t\t\n         \t\n\t\t\t\t<div class=\"col col_02\">\n\t\t\t\t\t<div class=\"mcol\">\n\t\t\t\t\t\n\t\t\t\t\t\t\n\t\t\t\t\t\t\n\t\t\t\t\t\t<div id=\"Dyn_2_1\" class=\"M42  \">\n\n<div class=\"module module-um md_style99\">\n   <div class=\"mouter\">\n\t<header class=\"mt mthide \">\n\t \n\t\n</header>\n\n\t<section class=\"mb\">\n\t\t<div class=\"minner\">\n\t\t\t<div class=\"meditor\">\n\t\t\t<a href=\"#start-C\" title='主要內容區' accesskey=\"C\" style=\"text-decoration:none\" id=\"start-C\">:::</a> \n\t\t\t</div>\n\t\t</div>\n\t</section>\n\t</div>\n</div>\n\n<!-- generated at Wed Aug 09 2023 15:16:47 --></div>\n\n\t\t\t\t\t\n\t\t\t\t\t\t\n\t\t\t\t\t\t\n\t\t\t\t\t\t<div id=\"Dyn_2_2\" class=\"M19848  \">\n\n<div class=\"module module-special md_style99\">\n<div class=\"mouter\">\n\t<header class=\"mt  mt-subhead\">\n\t \n\t<h2 class=\"mt-title\">HOT NEWS</h2><div class=\"mt-sub-title\">/焦點新聞/</div>\n</header>\n\n\t<section class=\"mb\">\n\t\t\n      \n      \t\n\t<div class=\"row listBS\">\n\t\n\t\n\t\t\n\t\t<div class=\"d-item h-il-td col-sm-12\">\n<div class=\"mbox\">\n\t<div class=\"d-img mimg-rounded\">\n\t\t<a><img src=\"/var/file/0/1000/pictures/74/m/mczh-tw400x400_small74167_384871514801.jpg\"  class=\"img-responsive\" alt=\"\" /></a>\n\t</div>\n\t<div class=\"d-txt\">\n\t\t<div class=\"mtitle\">\n\t\t\t\n\t\t\t<a href=\"https://www.nkust.edu.tw/p/406-1000-74167,r1363.php?Lang=zh-tw\"  title=\"創新建廠設計  高科大師生創業典範「萃思科技」成功完成日月光場域驗證\">\n\t\t\t\t創新建廠設計  高科大師生創業典範「萃思科技」成功完成日月光場域驗證\n\t\t\t</a>\n\t\t\t\n\t\t\t<i class=\"mdate after\">2023-10-25 </i>\n\t\t\t\n\t\t</div>\n\t\t<div class=\"mdetail\">\n\t\t\t\n   <div class=\"meditor\">\n\t\t\t<p style=\"text-align: justify;\">在2022年贏得國科會FITI創新創業激勵計畫「創業傑出獎」的國立高雄科技大學土木系團隊，其師生團隊在今(2023)年成立了「萃思科技股份有限公司」，也成功完成了與日月光合作的關鍵場域驗證，以AI完成半導體廠房的3D設計與建模，全新的AI-3D技術 (xModel跨域模型) 可自動化且快速地完成高科技廠房主系統的最佳化3D設計與建模。這項高難度的核心技術也是萃思科技在2022年成為FITI創業傑出獎隊伍的關鍵。</p>\n\n<p style=\"text-align: justify;\">昨(24)日，高雄市經發局號召眾科技業及創新團隊，為「數位孿生實驗室」共同揭牌，包...</p>\n\t</div>\n\t\t\t\n\t\t</div>\n\t</div>\n\t\n</div>\n</div>\n\n\t\t</div><div class=\"row listBS\">\n\t\n\t\t\n\t\t<div class=\"d-item h-il-td col-sm-12\">\n<div class=\"mbox\">\n\t<div class=\"d-img mimg-rounded\">\n\t\t<a><img src=\"/var/file/0/1000/pictures/793/m/mczh-tw400x400_small74156_212700205575.jpg\"  class=\"img-responsive\" alt=\"\" /></a>\n\t</div>\n\t<div class=\"d-txt\">\n\t\t<div class=\"mtitle\">\n\t\t\t\n\t\t\t<a href=\"https://www.nkust.edu.tw/p/406-1000-74156,r1363.php?Lang=zh-tw\"  title=\"高科大與勤誠興業攜手  共創模具技術新紀元\">\n\t\t\t\t高科大與勤誠興業攜手  共創模具技術新紀元\n\t\t\t</a>\n\t\t\t\n\t\t\t<i class=\"mdate after\">2023-10-25 </i>\n\t\t\t\n\t\t</div>\n\t\t<div class=\"mdetail\">\n\t\t\t\n   <div class=\"meditor\">\n\t\t\t<p style=\"text-align: justify;\">國立高雄科技大學和勤誠興業股份有限公司昨(24)日簽署合作意向書，同時舉行隆重的揭牌儀式，成立「模具開發及技術研發合作實驗室」，確認雙方未來在數個重要議題的合作關係，「模具開發及技術研發合作實驗室」將成為未來合作的核心，為師生和企業員工提供一個共同的工作環境，以促進知識交流和技術創新。</p>\n\n<p style=\"text-align: justify;\">勤誠興業作為全球雲端產業機電整合解決方案的領導品牌，以40年累積的研發能量，積極孵化多元研發人才。而機殼生產製造中的模具技術，是提升生產能量、降低成本的重要因素，對於維持勤誠的競爭力至關重要。勤誠嘉義廠自202...</p>\n\t</div>\n\t\t\t\n\t\t</div>\n\t</div>\n\t\n</div>\n</div>\n\n\t\t</div><div class=\"row listBS\">\n\t\n\t\t\n\t\t<div class=\"d-item h-il-td col-sm-12\">\n<div class=\"mbox\">\n\t<div class=\"d-img mimg-rounded\">\n\t\t<a><img src=\"/var/file/0/1000/pictures/725/m/mczh-tw400x400_small74101_2086447376.jpg\"  class=\"img-responsive\" alt=\"\" /></a>\n\t</div>\n\t<div class=\"d-txt\">\n\t\t<div class=\"mtitle\">\n\t\t\t\n\t\t\t<a href=\"https://www.nkust.edu.tw/p/406-1000-74101,r1363.php?Lang=zh-tw\"  title=\"世界太陽能車挑戰賽  高科大阿波羅車隊車檢通過已出發\">\n\t\t\t\t世界太陽能車挑戰賽  高科大阿波羅車隊車檢通過已出發\n\t\t\t</a>\n\t\t\t\n\t\t\t<i class=\"mdate after\">2023-10-23 </i>\n\t\t\t\n\t\t</div>\n\t\t<div class=\"mdetail\">\n\t\t\t\n   <div class=\"meditor\">\n\t\t\t<p style=\"text-align: justify;\">世界太陽能車挑戰賽(Bridgestone World Solar Challenge, BWSC 2023)昨(22)日在澳洲達爾文(Darwin)出發，國立高雄科技大學阿波羅太陽能車隊第七次參賽，今(23)進入賽事第二天，目標是縱貫整個澳洲駛抵3000公里外的阿得雷德(Adelaide)，目前阿波羅車隊抵達大約986公里處管制站(NRMA Control stop)。</p>\n\n<p style=\"text-align: justify;\">高科大阿波羅太陽能車隊今年派出9號太陽能車(Apollo IX)赴澳參賽，報名巡洋艦級(CSIRO Cruiser Cla...</p>\n\t</div>\n\t\t\t\n\t\t</div>\n\t</div>\n\t\n</div>\n</div>\n\n\t\t\n\t\n\t</div>\n\n\n      \n   \t\n\t\t\t<p class=\"more\"><a href=\"https://www.nkust.edu.tw/p/403-1000-1363-1.php?Lang=zh-tw\" title=\"> more news...\">> more news...</a></p>\n   \t\n\t</section>\n</div>\n</div>\n\n<!-- generated at Wed Oct 25 2023 14:20:03 --></div>\n\n\t\t\t\t\t\n\t\t\t\t\t</div>\n\t\t\t\t</div> \n\t\t\t \n\t\t\n\t\t\t\n\t\t\t\n\t\t\t\n\t\t\t\n\t\t\t\t\n        \t\t\n         \t\n\t\t\t\t<div class=\"col col_03\">\n\t\t\t\t\t<div class=\"mcol\">\n\t\t\t\t\t\n\t\t\t\t\t\t\n\t\t\t\t\t\t\n\t\t\t\t\t\t<div id=\"Dyn_3_1\" class=\"M43  \">\n\n<div class=\"module module-um md_style99\">\n   <div class=\"mouter\">\n\t<header class=\"mt mthide \">\n\t \n\t\n</header>\n\n\t<section class=\"mb\">\n\t\t<div class=\"minner\">\n\t\t\t<div class=\"meditor\">\n\t\t\t<a href=\"#start-R\" title='右方內容區' accesskey=\"R\" style=\"text-decoration:none\" id=\"start-R\">:::</a> \n\t\t\t</div>\n\t\t</div>\n\t</section>\n\t</div>\n</div>\n\n<!-- generated at Wed Aug 09 2023 15:16:47 --></div>\n\n\t\t\t\t\t\n\t\t\t\t\t\t\n\t\t\t\t\t\t\n\t\t\t\t\t\t<div id=\"Dyn_3_2\" class=\"M18918  \">\n\n<div class=\"module  module-rss md_style99\">\n<div class=\"minner\">\n\t<header class=\"mt  mt-subhead\">\n\t \n\t<h2 class=\"mt-title\">EVENTS and ANNOUNCEMENTS</h2><div class=\"mt-sub-title\">／活動公告／</div>\n</header>\n\n\t<section class=\"mb\">\n   \t\n\t<div class=\"row listBS\">\n\t\n\t\n\t\t\n\t\t<div class=\"d-item v-td col-sm-12\">\n<div class=\"mbox\">\n\t<div class=\"d-txt\">\n\t\t<div class=\"mtitle\">\n\t\t\t\n\t\t\t<a href=\"https://ws1.nkust.edu.tw/Activity/Home/Event?Sno=2023100310322661nta7 \" target=\"_blank\"   title=\"活動通知-海洋文學作家廖鴻基講座活動歡迎…(另開新視窗)\">\n\t\t\t\t活動通知-海洋文學作家廖鴻基講座活動歡迎…\n\t\t\t</a>\n\t\t\t\n\t\t\t\n\t\t\t\n\t\t</div>\n\t\t<div class=\"mdetail\">\n\t\t\t<i class=\"mdate before\">2023-10-26</i>\n\t\t\t<div class=\"meditor\">\n\t\t\t\n\t\t\t</div>\n\t\t\t\n\t\t</div>\n\t</div>\n\t\n</div>\n</div>\n\n\t\t</div><div class=\"row listBS\">\n\t\n\t\t\n\t\t<div class=\"d-item v-td col-sm-12\">\n<div class=\"mbox\">\n\t<div class=\"d-txt\">\n\t\t<div class=\"mtitle\">\n\t\t\t\n\t\t\t<a href=\"https://ws1.nkust.edu.tw/Activity/Home/Event?Sno=20230913145150PT0RO9 \" target=\"_blank\"   title=\"【精進自我，迎向未來】系列講座_出版業的…(另開新視窗)\">\n\t\t\t\t【精進自我，迎向未來】系列講座_出版業的…\n\t\t\t</a>\n\t\t\t\n\t\t\t\n\t\t\t\n\t\t</div>\n\t\t<div class=\"mdetail\">\n\t\t\t<i class=\"mdate before\">2023-10-26</i>\n\t\t\t<div class=\"meditor\">\n\t\t\t\n\t\t\t</div>\n\t\t\t\n\t\t</div>\n\t</div>\n\t\n</div>\n</div>\n\n\t\t</div><div class=\"row listBS\">\n\t\n\t\t\n\t\t<div class=\"d-item v-td col-sm-12\">\n<div class=\"mbox\">\n\t<div class=\"d-txt\">\n\t\t<div class=\"mtitle\">\n\t\t\t\n\t\t\t<a href=\"https://ws1.nkust.edu.tw/Activity/Home/Event?Sno=20231019125953k4kD81 \" target=\"_blank\"   title=\"【想像驅動未來-校慶歌唱大賽】建工初賽(另開新視窗)\">\n\t\t\t\t【想像驅動未來-校慶歌唱大賽】建工初賽\n\t\t\t</a>\n\t\t\t\n\t\t\t\n\t\t\t\n\t\t</div>\n\t\t<div class=\"mdetail\">\n\t\t\t<i class=\"mdate before\">2023-10-26</i>\n\t\t\t<div class=\"meditor\">\n\t\t\t\n\t\t\t</div>\n\t\t\t\n\t\t</div>\n\t</div>\n\t\n</div>\n</div>\n\n\t\t</div><div class=\"row listBS\">\n\t\n\t\t\n\t\t<div class=\"d-item v-td col-sm-12\">\n<div class=\"mbox\">\n\t<div class=\"d-txt\">\n\t\t<div class=\"mtitle\">\n\t\t\t\n\t\t\t<a href=\"https://ws1.nkust.edu.tw/Activity/Home/Event?Sno=20230928113015nK7ELo \" target=\"_blank\"   title=\"10/27(五) 112-1 English Corner - Distr…(另開新視窗)\">\n\t\t\t\t10/27(五) 112-1 English Corner - Distr…\n\t\t\t</a>\n\t\t\t\n\t\t\t\n\t\t\t\n\t\t</div>\n\t\t<div class=\"mdetail\">\n\t\t\t<i class=\"mdate before\">2023-10-27</i>\n\t\t\t<div class=\"meditor\">\n\t\t\t\n\t\t\t</div>\n\t\t\t\n\t\t</div>\n\t</div>\n\t\n</div>\n</div>\n\n\t\t</div><div class=\"row listBS\">\n\t\n\t\t\n\t\t<div class=\"d-item v-td col-sm-12\">\n<div class=\"mbox\">\n\t<div class=\"d-txt\">\n\t\t<div class=\"mtitle\">\n\t\t\t\n\t\t\t<a href=\"https://ws1.nkust.edu.tw/Activity/Home/Event?Sno=20230928113015nK7ELo \" target=\"_blank\"   title=\"10/27(五) 112-1 English Corner - Distr…(另開新視窗)\">\n\t\t\t\t10/27(五) 112-1 English Corner - Distr…\n\t\t\t</a>\n\t\t\t\n\t\t\t\n\t\t\t\n\t\t</div>\n\t\t<div class=\"mdetail\">\n\t\t\t<i class=\"mdate before\">2023-10-27</i>\n\t\t\t<div class=\"meditor\">\n\t\t\t\n\t\t\t</div>\n\t\t\t\n\t\t</div>\n\t</div>\n\t\n</div>\n</div>\n\n\t\t</div><div class=\"row listBS\">\n\t\n\t\t\n\t\t<div class=\"d-item v-td col-sm-12\">\n<div class=\"mbox\">\n\t<div class=\"d-txt\">\n\t\t<div class=\"mtitle\">\n\t\t\t\n\t\t\t<a href=\"https://ws1.nkust.edu.tw/Activity/Home/Event?Sno=20230911154233nE9Yd1 \" target=\"_blank\"   title=\"美感微學程-大人的畫畫課(另開新視窗)\">\n\t\t\t\t美感微學程-大人的畫畫課\n\t\t\t</a>\n\t\t\t\n\t\t\t\n\t\t\t\n\t\t</div>\n\t\t<div class=\"mdetail\">\n\t\t\t<i class=\"mdate before\">2023-10-06</i>\n\t\t\t<div class=\"meditor\">\n\t\t\t\n\t\t\t</div>\n\t\t\t\n\t\t</div>\n\t</div>\n\t\n</div>\n</div>\n\n\t\t</div><div class=\"row listBS\">\n\t\n\t\t\n\t\t<div class=\"d-item v-td col-sm-12\">\n<div class=\"mbox\">\n\t<div class=\"d-txt\">\n\t\t<div class=\"mtitle\">\n\t\t\t\n\t\t\t<a href=\"https://ws1.nkust.edu.tw/Activity/Home/Event?Sno=20231013090302Gw03OI \" target=\"_blank\"   title=\"教師與銓日儀企業交流會(建工校區)(另開新視窗)\">\n\t\t\t\t教師與銓日儀企業交流會(建工校區)\n\t\t\t</a>\n\t\t\t\n\t\t\t\n\t\t\t\n\t\t</div>\n\t\t<div class=\"mdetail\">\n\t\t\t<i class=\"mdate before\">2023-10-27</i>\n\t\t\t<div class=\"meditor\">\n\t\t\t\n\t\t\t</div>\n\t\t\t\n\t\t</div>\n\t</div>\n\t\n</div>\n</div>\n\n\t\t\n\t\n\t</div>\n\n\n   \t\n\t\t\t<p class=\"more\"><a href=\"/p/424-1000-7-1.php\"  title=\">高科大活動訊息平台\" >>高科大活動訊息平台</a></p>\n   \t\n\t</section>\n</div>\n</div>\n\n\n\n<!-- generated at Thu Oct 26 2023 13:23:47 --></div>\n\n\t\t\t\t\t\n\t\t\t\t\t</div>\n\t\t\t\t</div> \n\t\t\t \n\t\t\n\t</div>\n</div>\n\t\n\n\t\n\t\n<div class=\"row col2 row_1\">\n\t<div class=\"mrow container\">\n\t\t\n\t\t\t\n\t\t\t\n\t\t\t\n\t\t\t \n\t\t\n\t\t\t\n\t\t\t\n\t\t\t\n\t\t\t\n\t\t\t\t\n        \t\t\n         \t\n\t\t\t\t<div class=\"col col_02\">\n\t\t\t\t\t<div class=\"mcol\">\n\t\t\t\t\t\n\t\t\t\t\t\t\n\t\t\t\t\t\t\n\t\t\t\t\t\t<div id=\"Dyn_1_2_1\" class=\"M10010  \">\n\n<div class=\"module module-special md_style1\">\n<div class=\"mouter\">\n\t<header class=\"mt  mt-subhead\">\n\t \n\t<h2 class=\"mt-title\">HONOR</h2><div class=\"mt-sub-title\">／榮譽肯定／</div>\n</header>\n\n\t<section class=\"mb\">\n\t\t\n      \n      \t\n\t<div class=\"row listBS\">\n\t\n\t\n\t\t\n\t\t<div class=\"d-item d-title col-sm-12\">\n<div class=\"mbox\">\n\t<div class=\"d-txt\">\n\t\t<div class=\"mtitle\">\n\t\t\t\n\t\t\t<a href=\"https://www.nkust.edu.tw/p/406-1000-73303,r13.php\"  title=\"賀！航運管理系曾文瑞教授榮獲「2023全國開放教育優良課程」優選獎\">\n\t\t\t\t\n\t\t\t\t賀！航運管理系曾文瑞教授榮獲「2023全國開放教育優良課程」優選獎\n\t\t\t</a>\n\t\t\t\n\t\t\t\n\t\t\t\n\t\t</div>\n\t</div>\n\t\n</div>\n</div>\n\n\t\t</div><div class=\"row listBS\">\n\t\n\t\t\n\t\t<div class=\"d-item d-title col-sm-12\">\n<div class=\"mbox\">\n\t<div class=\"d-txt\">\n\t\t<div class=\"mtitle\">\n\t\t\t\n\t\t\t<a href=\"https://www.nkust.edu.tw/p/406-1000-73114,r13.php\"  title=\"賀！金融資訊系賴青瑋同學榮獲「2023金融投資明日之星-AI程式交易策略挑戰賽」程式設計-進階組冠軍\">\n\t\t\t\t\n\t\t\t\t賀！金融資訊系賴青瑋同學榮獲「2023金融投資明日之星-AI程式交易策略挑戰賽」程式設計-進階組冠軍\n\t\t\t</a>\n\t\t\t\n\t\t\t\n\t\t\t\n\t\t</div>\n\t</div>\n\t\n</div>\n</div>\n\n\t\t</div><div class=\"row listBS\">\n\t\n\t\t\n\t\t<div class=\"d-item d-title col-sm-12\">\n<div class=\"mbox\">\n\t<div class=\"d-txt\">\n\t\t<div class=\"mtitle\">\n\t\t\t\n\t\t\t<a href=\"https://www.nkust.edu.tw/p/406-1000-72098,r13.php\" target=\"_blank\"   title=\"賀！國際企業系陳昇鴻老師指導潘欣喬博士生榮獲「2023年財務金融學刊研究論文獎」(另開新視窗)\">\n\t\t\t\t\n\t\t\t\t賀！國際企業系陳昇鴻老師指導潘欣喬博士生榮獲「2023年財務金融學刊研究論文獎」\n\t\t\t</a>\n\t\t\t\n\t\t\t\n\t\t\t\n\t\t</div>\n\t</div>\n\t\n</div>\n</div>\n\n\t\t</div><div class=\"row listBS\">\n\t\n\t\t\n\t\t<div class=\"d-item d-title col-sm-12\">\n<div class=\"mbox\">\n\t<div class=\"d-txt\">\n\t\t<div class=\"mtitle\">\n\t\t\t\n\t\t\t<a href=\"https://www.nkust.edu.tw/p/406-1000-71119,r13.php\"  title=\"賀！高科大境外生參加「2023愛河端午龍舟嘉年華競賽」勇奪國際混合組第三名\">\n\t\t\t\t\n\t\t\t\t賀！高科大境外生參加「2023愛河端午龍舟嘉年華競賽」勇奪國際混合組第三名\n\t\t\t</a>\n\t\t\t\n\t\t\t\n\t\t\t\n\t\t</div>\n\t</div>\n\t\n</div>\n</div>\n\n\t\t</div><div class=\"row listBS\">\n\t\n\t\t\n\t\t<div class=\"d-item d-title col-sm-12\">\n<div class=\"mbox\">\n\t<div class=\"d-txt\">\n\t\t<div class=\"mtitle\">\n\t\t\t\n\t\t\t<a href=\"https://www.nkust.edu.tw/p/406-1000-70134,r13.php\"  title=\"賀！馬來西亞資管系僑生張文嫣榮獲「2023年僑務委員會應屆畢業傑出僑生委員長獎」\">\n\t\t\t\t\n\t\t\t\t賀！馬來西亞資管系僑生張文嫣榮獲「2023年僑務委員會應屆畢業傑出僑生委員長獎」\n\t\t\t</a>\n\t\t\t\n\t\t\t\n\t\t\t\n\t\t</div>\n\t</div>\n\t\n</div>\n</div>\n\n\t\t\n\t\n\t</div>\n\n\n      \n   \t\n\t\t\t<p class=\"more\"><a href=\"https://www.nkust.edu.tw/p/403-1000-13-1.php\" title=\"更多榮譽肯定...\">更多榮譽肯定...</a></p>\n   \t\n\t</section>\n</div>\n</div>\n\n</div>\n\n\t\t\t\t\t\n\t\t\t\t\t</div>\n\t\t\t\t</div> \n\t\t\t \n\t\t\n\t\t\t\n\t\t\t\n\t\t\t\n\t\t\t\n\t\t\t\t\n        \t\t\n         \t\n\t\t\t\t<div class=\"col col_03\">\n\t\t\t\t\t<div class=\"mcol\">\n\t\t\t\t\t\n\t\t\t\t\t\t\n\t\t\t\t\t\t\n\t\t\t\t\t\t<div id=\"Dyn_1_3_1\" class=\"M18922  \">\n\n<div class=\"module  module-rss md_style99\">\n<div class=\"minner\">\n\t<header class=\"mt  mt-subhead\">\n\t \n\t<h2 class=\"mt-title\">MEDIA CONTRIBUTE</h2><div class=\"mt-sub-title\">／內容共享／</div>\n</header>\n\n\t<section class=\"mb\">\n   \t\n\t<div class=\"row listBS\">\n\t\n\t\n\t\t\n\t\t<div class=\"d-item d-title col-sm-12\">\n<div class=\"mbox\">\n\t<div class=\"d-txt\">\n\t\t<div class=\"mtitle\">\n\t\t\t\n\t\t\t<a href=\"https://www.gvm.com.tw/article/107007\" target=\"_blank\"   title=\"達發上市即「破發」，聯發科小金雞還能生金...(另開新視窗)\">\n\t\t\t\t\n\t\t\t\t達發上市即「破發」，聯發科小金雞還能生金...\n\t\t\t</a>\n\t\t\t\n\t\t\t\n\t\t\t\n\t\t</div>\n\t</div>\n\t\n</div>\n</div>\n\n\t\t</div><div class=\"row listBS\">\n\t\n\t\t\n\t\t<div class=\"d-item d-title col-sm-12\">\n<div class=\"mbox\">\n\t<div class=\"d-txt\">\n\t\t<div class=\"mtitle\">\n\t\t\t\n\t\t\t<a href=\"https://www.gvm.com.tw/article/106999\" target=\"_blank\"   title=\"台中四方電巴傳欠薪罷工！背後是業者被割韭...(另開新視窗)\">\n\t\t\t\t\n\t\t\t\t台中四方電巴傳欠薪罷工！背後是業者被割韭...\n\t\t\t</a>\n\t\t\t\n\t\t\t\n\t\t\t\n\t\t</div>\n\t</div>\n\t\n</div>\n</div>\n\n\t\t</div><div class=\"row listBS\">\n\t\n\t\t\n\t\t<div class=\"d-item d-title col-sm-12\">\n<div class=\"mbox\">\n\t<div class=\"d-txt\">\n\t\t<div class=\"mtitle\">\n\t\t\t\n\t\t\t<a href=\"https://www.gvm.com.tw/article/106986\" target=\"_blank\"   title=\"11月掛牌上櫃！工業電腦新兵宸曜如何不靠...(另開新視窗)\">\n\t\t\t\t\n\t\t\t\t11月掛牌上櫃！工業電腦新兵宸曜如何不靠...\n\t\t\t</a>\n\t\t\t\n\t\t\t\n\t\t\t\n\t\t</div>\n\t</div>\n\t\n</div>\n</div>\n\n\t\t</div><div class=\"row listBS\">\n\t\n\t\t\n\t\t<div class=\"d-item d-title col-sm-12\">\n<div class=\"mbox\">\n\t<div class=\"d-txt\">\n\t\t<div class=\"mtitle\">\n\t\t\t\n\t\t\t<a href=\"https://www.gvm.com.tw/article/106442\" target=\"_blank\"   title=\"BLACKPINK、COLDPLAY、林...(另開新視窗)\">\n\t\t\t\t\n\t\t\t\tBLACKPINK、COLDPLAY、林...\n\t\t\t</a>\n\t\t\t\n\t\t\t\n\t\t\t\n\t\t</div>\n\t</div>\n\t\n</div>\n</div>\n\n\t\t</div><div class=\"row listBS\">\n\t\n\t\t\n\t\t<div class=\"d-item d-title col-sm-12\">\n<div class=\"mbox\">\n\t<div class=\"d-txt\">\n\t\t<div class=\"mtitle\">\n\t\t\t\n\t\t\t<a href=\"https://www.gvm.com.tw/article/106249\" target=\"_blank\"   title=\"令人成癮的魔力？專家：你應該戒掉短影音的...(另開新視窗)\">\n\t\t\t\t\n\t\t\t\t令人成癮的魔力？專家：你應該戒掉短影音的...\n\t\t\t</a>\n\t\t\t\n\t\t\t\n\t\t\t\n\t\t</div>\n\t</div>\n\t\n</div>\n</div>\n\n\t\t\n\t\n\t</div>\n\n\n   \t\n\t\t\t<p class=\"more\"><a href=\"/p/424-1000-8-1.php\"  title=\"內容共享：遠見雜誌\" >內容共享：遠見雜誌</a></p>\n   \t\n\t</section>\n</div>\n</div>\n\n\n\n<!-- generated at Thu Oct 26 2023 13:30:22 --></div>\n\n\t\t\t\t\t\n\t\t\t\t\t</div>\n\t\t\t\t</div> \n\t\t\t \n\t\t\n\t</div>\n</div>\n\t\n\n\t\n\t\n<div class=\"row col1 row_2\">\n\t<div class=\"mrow container\">\n\t\t\n\t\t\t\n\t\t\t\n\t\t\t\n\t\t\t \n\t\t\n\t\t\t\n\t\t\t\n\t\t\t\n\t\t\t\n\t\t\t\t\n        \t\t\n         \t\n\t\t\t\t<div class=\"col col_02\">\n\t\t\t\t\t<div class=\"mcol\">\n\t\t\t\t\t\n\t\t\t\t\t\t\n\t\t\t\t\t\t\n\t\t\t\t\t\t<div id=\"Dyn_2_2_1\" class=\"M10017  \">\n\n<script>\n$(document).ready(function() {\n\t$('#a2480f95040ba01f7b5f02d8916f9fe5b_Div .nav-tabs a').keydown(function (e) {\n\t\tif (e.shiftKey && e.keyCode === 9) {\n\t   \t$(this).parent().prev().children().tab('show');\n\t   \t$(this).parent().prev().children().prop(\"tabindex\",\"0\");\n  \t\t}\n\t});\n\t$('#a2480f95040ba01f7b5f02d8916f9fe5b_Div .nav-tabs a').focus(function (e) {\n\t\ta2480f95040ba01f7b5f02d8916f9fe5b_goto(this);\n\t});\n});\nfunction a2480f95040ba01f7b5f02d8916f9fe5b_goto(obj){\n\t\t$(obj).tab('show');\n\t\t$(obj).prop(\"tabindex\",\"0\");\n\t\t$(obj).parent().siblings().children().prop(\"tabindex\",\"-1\");\n\t\t$('#sm_a2480f95040ba01f7b5f02d8916f9fe5b_0').prop(\"tabindex\",\"0\");\n}\n</script>\n<div id=\"a2480f95040ba01f7b5f02d8916f9fe5b_Div\" class=\"module module-complex md_style1\">\n\t<div class=\"minner\">\n\t\t<header class=\"mt mthide \">\n\t \n\t\n</header>\n\n\t\t<section class=\"mb\">\n\t\t\t<nav><ul class=\"nav nav-tabs\">\n\t\t\t\n\t\t\t\n\t\t\t<li class=\"active\"><a title=\"最新消息\"  id=\"sm_a2480f95040ba01f7b5f02d8916f9fe5b_0\"  tabindex=\"0\" href=\"#cmb_1_0\" data-toggle=\"tab\" ><h2>最新消息</h2></a></li>\n\t\t\t\n\t\t\t\n\t\t\t\n\t\t\t\n\t\t\t\n\t\t\t<li><a title=\"行政公告\" id=\"sm_a2480f95040ba01f7b5f02d8916f9fe5b_1\"  tabindex=\"-1\" href=\"#cmb_1_1\" data-toggle=\"tab\"><h2>行政公告</h2></a></li>\n\t\t\t\n\t\t\t\n\t\t\t\n\t\t\t\n\t\t\t<li><a title=\"學術公告\" id=\"sm_a2480f95040ba01f7b5f02d8916f9fe5b_2\"  tabindex=\"-1\" href=\"#cmb_1_2\" data-toggle=\"tab\"><h2>學術公告</h2></a></li>\n\t\t\t\n\t\t\t\n\t\t\t\n\t\t\t\n\t\t\t<li><a title=\"活動訊息\" id=\"sm_a2480f95040ba01f7b5f02d8916f9fe5b_3\"  tabindex=\"-1\" href=\"#cmb_1_3\" data-toggle=\"tab\"><h2>活動訊息</h2></a></li>\n\t\t\t\n\t\t\t\n\t\t\t\n\t\t\t\n\t\t\t<li><a title=\"校內徵才\" id=\"sm_a2480f95040ba01f7b5f02d8916f9fe5b_4\"  tabindex=\"-1\" href=\"#cmb_1_4\" data-toggle=\"tab\"><h2>校內徵才</h2></a></li>\n\t\t\t\n\t\t\t\n\t\t\t\n\t\t\t\n\t\t\t<li><a title=\"校外職缺\" id=\"sm_a2480f95040ba01f7b5f02d8916f9fe5b_5\"  tabindex=\"-1\" href=\"#cmb_1_5\" data-toggle=\"tab\"><h2>校外職缺</h2></a></li>\n\t\t\t\n\t\t\t\n\t\t\t</ul></nav>\n\t\t\t<div class=\"tab-content\">\n\t\t\t\t\n\t\t\t\t\n\t\t\t\t\n\t\t\t\t\n\t\t\t\t\n\t\t\t\t\t<div class=\"tab-pane fade in active\" id=\"cmb_1_0\">\n\t\t\t\t\t\t<div id=\"sm_div_cmb_1_10431\"></div>\n\t               <script>$(document).ready(function() {$.hajaxOpenUrl('/app/index.php?Action=mobileloadmod&Type=mobile_asso_cg_mstr&Nbr=1001','#sm_div_cmb_1_10431','',function(){menuDropAct(0);});})</script>\n\t\t\t\t\t\t\n\t\t\t\t\t\t\t<a id=\"sm_a2480f95040ba01f7b5f02d8916f9fe5b_1_href\" href=\"\" onkeyup=\"$('#sm_a2480f95040ba01f7b5f02d8916f9fe5b_1').focus();\"><img  alt=\"\" src=\"/images/clear.gif\" /></a>\n\t\t\t\t\t\t\n\t\t\t\t\t</div>\n\t\t\t\t\n\t\t\t\t\n\t\t\t\t\n\t\t\t\t\n\t\t\t\t\n\t\t\t\t\n\t\t\t\t\n\t\t\t\t\n\t\t\t\t\n\t\t\t\t\t<div class=\"tab-pane fade\" id=\"cmb_1_1\">\n\t\t\t\t\t\t<div id=\"sm_div_cmb_1_10304\"></div>\n                  <script>$(document).ready(function() {$.hajaxOpenUrl('/app/index.php?Action=mobileloadmod&Type=mobile_asso_cg_mstr&Nbr=1000','#sm_div_cmb_1_10304','',function(){menuDropAct(0);});})</script>\n\n\t\t\t\t\t\t\n\t\t\t\t\t\t\t<a id=\"sm_a2480f95040ba01f7b5f02d8916f9fe5b_2_href\" href=\"\" onkeyup=\"$('#sm_a2480f95040ba01f7b5f02d8916f9fe5b_2').focus();\"><img  alt=\"\" src=\"/images/clear.gif\" /></a>\n\t\t\t\t\t\t\n\n\t\t\t\t\t</div>\n            \n\t\t\t\t\n\t\t\t\t\n\t\t\t\t\n\t\t\t\t\n\t\t\t\t\n\t\t\t\t\n\t\t\t\t\n\t\t\t\t\t<div class=\"tab-pane fade\" id=\"cmb_1_2\">\n\t\t\t\t\t\t<div id=\"sm_div_cmb_1_10432\"></div>\n                  <script>$(document).ready(function() {$.hajaxOpenUrl('/app/index.php?Action=mobileloadmod&Type=mobile_asso_cg_mstr&Nbr=1002','#sm_div_cmb_1_10432','',function(){menuDropAct(0);});})</script>\n\n\t\t\t\t\t\t\n\t\t\t\t\t\t\t<a id=\"sm_a2480f95040ba01f7b5f02d8916f9fe5b_3_href\" href=\"\" onkeyup=\"$('#sm_a2480f95040ba01f7b5f02d8916f9fe5b_3').focus();\"><img  alt=\"\" src=\"/images/clear.gif\" /></a>\n\t\t\t\t\t\t\n\n\t\t\t\t\t</div>\n            \n\t\t\t\t\n\t\t\t\t\n\t\t\t\t\n\t\t\t\t\n\t\t\t\t\n\t\t\t\t\n\t\t\t\t\n\t\t\t\t\t<div class=\"tab-pane fade\" id=\"cmb_1_3\">\n\t\t\t\t\t\t<div id=\"sm_div_cmb_1_10433\"></div>\n                  <script>$(document).ready(function() {$.hajaxOpenUrl('/app/index.php?Action=mobileloadmod&Type=mobile_asso_cg_mstr&Nbr=1003','#sm_div_cmb_1_10433','',function(){menuDropAct(0);});})</script>\n\n\t\t\t\t\t\t\n\t\t\t\t\t\t\t<a id=\"sm_a2480f95040ba01f7b5f02d8916f9fe5b_4_href\" href=\"\" onkeyup=\"$('#sm_a2480f95040ba01f7b5f02d8916f9fe5b_4').focus();\"><img  alt=\"\" src=\"/images/clear.gif\" /></a>\n\t\t\t\t\t\t\n\n\t\t\t\t\t</div>\n            \n\t\t\t\t\n\t\t\t\t\n\t\t\t\t\n\t\t\t\t\n\t\t\t\t\n\t\t\t\t\n\t\t\t\t\n\t\t\t\t\t<div class=\"tab-pane fade\" id=\"cmb_1_4\">\n\t\t\t\t\t\t<div id=\"sm_div_cmb_1_15062\"></div>\n                  <script>$(document).ready(function() {$.hajaxOpenUrl('/app/index.php?Action=mobileloadmod&Type=mobile_asso_cg_mstr&Nbr=1018','#sm_div_cmb_1_15062','',function(){menuDropAct(0);});})</script>\n\n\t\t\t\t\t\t\n\t\t\t\t\t\t\t<a id=\"sm_a2480f95040ba01f7b5f02d8916f9fe5b_5_href\" href=\"\" onkeyup=\"$('#sm_a2480f95040ba01f7b5f02d8916f9fe5b_5').focus();\"><img  alt=\"\" src=\"/images/clear.gif\" /></a>\n\t\t\t\t\t\t\n\n\t\t\t\t\t</div>\n            \n\t\t\t\t\n\t\t\t\t\n\t\t\t\t\n\t\t\t\t\n\t\t\t\t\n\t\t\t\t\n\t\t\t\t\n\t\t\t\t\t<div class=\"tab-pane fade\" id=\"cmb_1_5\">\n\t\t\t\t\t\t<div id=\"sm_div_cmb_1_11282\"></div>\n                  <script>$(document).ready(function() {$.hajaxOpenUrl('/app/index.php?Action=mobileloadmod&Type=mobile_asso_cg_mstr&Nbr=1006','#sm_div_cmb_1_11282','',function(){menuDropAct(0);});})</script>\n\n\t\t\t\t\t\t\n\n\t\t\t\t\t</div>\n            \n\t\t\t\t\n\t\t\t\t\n\t\t\t</div>\n\t\t</section>\n\t</div>\n</div>\n\n<!-- generated at Thu Oct 26 2023 10:34:17 --></div>\n\n\t\t\t\t\t\n\t\t\t\t\t</div>\n\t\t\t\t</div> \n\t\t\t \n\t\t\n\t\t\t\n\t\t\t\n\t\t\t\n\t\t\t \n\t\t\n\t</div>\n</div>\n\t\n\n\t\n\t\n<div class=\"row col1 row_3\">\n\t<div class=\"mrow container\">\n\t\t\n\t\t\t\n\t\t\t\n\t\t\t\n\t\t\t \n\t\t\n\t\t\t\n\t\t\t\n\t\t\t\n\t\t\t\n\t\t\t\t\n        \t\t\n         \t\n\t\t\t\t<div class=\"col col_02\">\n\t\t\t\t\t<div class=\"mcol\">\n\t\t\t\t\t\n\t\t\t\t\t\t\n\t\t\t\t\t\t\n\t\t\t\t\t\t<div id=\"Dyn_3_2_1\" class=\"M10033  \">\n\n<div class=\"module module-um md_style1\">\n   <div class=\"mouter\">\n\t<header class=\"mt mtimg \">\n\t<h2><img src=\"/var/file/0/1000/title/mobilemotitle_mobile_um_mstr_7_3395197_95884.png\"    alt=\"A-影音新聞_左&amp;右-1080131-上架\" ></h2> \n\t\n</header>\n\n\t<section class=\"mb\">\n\t\t<div class=\"minner\">\n\t\t\t<div class=\"meditor\">\n\t\t\t\n  <div class=\"module-compound\">\n    <!--左邊-->\n    <div class=\"mldule_left\">\n      <iframe allowfullscreen frameborder=\"0\" src=\"https://www.youtube.com/embed/ZuwvCFJ4ezY\" title=\"111年度 菁英學生大放異彩，高科大是您的最佳選擇\"></iframe>\n      <div class=\"d-txt\">\n        <p><!--<i class=\"mdate\">2017-08-02 </i>--><a href=\"https://youtu.be/ZuwvCFJ4ezY\" target=\"_blank\" title=\"111年度 菁英學生大放異彩，高科大是您的最佳選擇_另開視窗\"><span id=\"cke_bm_289S\" style=\"display: none;\">&nbsp;</span></a></p>\n        <p><a href=\"https://youtu.be/70_aVOfaZTc\" target=\"_blank\" title=\"111年度 菁英學生大放異彩，高科大是您的最佳選擇_另開視窗\">111年度 菁英學生大放異彩，高科大是您的最佳選擇<span id=\"cke_bm_289E\" style=\"display: none;\">&nbsp;</span></a></p>\n      </div>\n    </div><!--右邊-->\n    <div class=\"mldule_right\">\n      <!--1-->\n      <div class=\"d-item\">\n        <iframe allowfullscreen frameborder=\"0\" src=\"https://www.youtube.com/embed/70_aVOfaZTc\" title=\"安居桃花源．港都山線韌性城鄉營建計畫\"></iframe>\n        <div class=\"d-txt\">\n          <p><a href=\"https://youtube.be/70_aVOfaZTc\" target=\"_blank\" title=\"安居桃花源．港都山線韌性城鄉營建計畫 _另開視窗\"><span id=\"cke_bm_290S\" style=\"display: none;\">&nbsp;</span>安居桃花源．港都山線韌性城鄉營建計畫<span id=\"cke_bm_290E\" style=\"display: none;\">&nbsp;</span></a></p>\n        </div>\n      </div><!--1--><!--2 開始-->\n      <div class=\"d-item\">\n        <iframe allowfullscreen frameborder=\"0\" src=\"https://www.youtube.com/embed/3UQRZn29f3A\" title=\"高科大體驗學習練功坊\"></iframe>\n        <div class=\"d-txt\">\n          <p><a href=\"https://youtube.be/3UQRZn29f3A\" target=\"_blank\" title=\"高科大體驗學習練功坊 _另開視窗\"><span id=\"cke_bm_290S\" style=\"display: none;\">&nbsp;</span>高科大體驗學習練功坊<span id=\"cke_bm_290E\" style=\"display: none;\">&nbsp;</span></a></p>\n        </div>\n      </div><!--2 結束--><!--3-->\n      <div class=\"d-item\">\n        <iframe allowfullscreen frameborder=\"0\" src=\"https://www.youtube.com/embed/dbkLz1EiLS4\" title=\"高科大之歌NKUST MV\"></iframe>\n        <div class=\"d-txt\">\n          <p><a href=\"https://www.youtube.com/watch?app=desktop&amp;v=dbkLz1EiLS4&amp;feature=youtu.be\" target=\"_blank\" title=\"高科大之歌NKUST MV _另開視窗\"><span id=\"cke_bm_290S\" style=\"display: none;\">&nbsp;</span>高科大之歌NKUST MV<span id=\"cke_bm_290E\" style=\"display: none;\">&nbsp;</span></a></p>\n        </div>\n      </div><!--3-->\n    </div>\n  </div>\n  <p class=\"more\"><a href=\"https://www.youtube.com/channel/UCk7QGAi2QAFrH63mPPX-apw\" target=\"_blank\" title=\"更多高科大影音(另開視窗)\">+更多影音</a></p>\n  <style type=\"text/css\">\n  .mldule_left .d-txt, .mldule_right .d-txt {\n        padding: .2em 0;\n        text-align: center;\n     }\n     .mldule_right .d-txt h5 a, .mldule_left .d-txt h5 a {\n        font-weight: bold;\n        font-size: 1.01em;\n     }\n  </style> \n\t\t\t</div>\n\t\t</div>\n\t</section>\n\t</div>\n</div>\n\n<!-- generated at Wed Aug 09 2023 15:16:48 --></div>\n\n\t\t\t\t\t\n\t\t\t\t\t</div>\n\t\t\t\t</div> \n\t\t\t \n\t\t\n\t\t\t\n\t\t\t\n\t\t\t\n\t\t\t \n\t\t\n\t</div>\n</div>\n\t\n\n\t\n\t\n<div class=\"row col1 row_4\">\n\t<div class=\"mrow container\">\n\t\t\n\t\t\t\n\t\t\t\n\t\t\t\n\t\t\t \n\t\t\n\t\t\t\n\t\t\t\n\t\t\t\n\t\t\t\n\t\t\t\t\n        \t\t\n         \t\n\t\t\t\t<div class=\"col col_02\">\n\t\t\t\t\t<div class=\"mcol\">\n\t\t\t\t\t\n\t\t\t\t\t\t\n\t\t\t\t\t\t\n\t\t\t\t\t\t<div id=\"Dyn_4_2_1\" class=\"M10020  \">\n\n<div class=\"module module-link md_style2\">\n<div class=\"mouter\">\n\t<header class=\"mt \">\n\t \n\t<h2 class=\"mt-title\">LINKS <br/>/常用連結/</h2>\n</header>\n\n\t<section class=\"mb\">\n\t\t\n      \n      \t\n\t<div class=\"row listBS\">\n\t\n\t\n\t\t\n\t\t<div class=\"d-item d-title col-sm-6\">\n<div class=\"mbox\">\n\t<div class=\"d-txt\">\n\t\t<div class=\"mtitle\">\n\t\t\t\n\t\t\t<a href=\"/p/412-1000-2032.php\"  title=\"校內連結\">\n\t\t\t\t\n\t\t\t\t校內連結\n\t\t\t</a>\n\t\t\t\n\t\t\t\n\t\t\t\n\t\t</div>\n\t</div>\n\t\n</div>\n</div>\n\n\t\t\n\t\n\t\t\n\t\t<div class=\"d-item d-title col-sm-6\">\n<div class=\"mbox\">\n\t<div class=\"d-txt\">\n\t\t<div class=\"mtitle\">\n\t\t\t\n\t\t\t<a href=\"/p/412-1000-2033.php\"  title=\"校外連結\">\n\t\t\t\t\n\t\t\t\t校外連結\n\t\t\t</a>\n\t\t\t\n\t\t\t\n\t\t\t\n\t\t</div>\n\t</div>\n\t\n</div>\n</div>\n\n\t\t\n\t\n\t</div>\n\n\n      \n   \t\n\t</section>\n</div>\n</div>\n\n<!-- generated at Wed Aug 09 2023 15:16:48 --></div>\n\n\t\t\t\t\t\n\t\t\t\t\t</div>\n\t\t\t\t</div> \n\t\t\t \n\t\t\n\t\t\t\n\t\t\t\n\t\t\t\n\t\t\t \n\t\t\n\t</div>\n</div>\n\t\n\n</div>\n</div>\n\n\n\n<div id=\"Dyn_footer\">\n<div class=\"footer\">\n<div class=\"minner \">\n\n<div id=\"Dyn_mobilecounter\" class=\"M45 M45_0  \"></div>\n<script language=\"javascript\" >\n $(document).ready(function(){ $.hajaxOpenUrl('/app/index.php?Action=mobileloadmod&Type=mobilecounter&Nbr=','#Dyn_mobilecounter');\n });\n </script>\n\n\n\n\n\n\n<div class=\"copyright\">\n<div class=\"meditor\">\n\t<meta name = \"format-detection\" content = \"telephone=no\">\n<div class=\"bt_first\" style=\"position:relative;\"><a accesskey=\"B\" href=\"#B\" name=\"B\" style=\"position:absolute; left:1.6em; top:8px; color:#fff;\">:::</a>\n<ul>\n\t<li>第一校區 824005 高雄市燕巢區大學路1號<br />\n\t&nbsp; &nbsp; &nbsp; &nbsp; &nbsp; &nbsp; &nbsp; &nbsp;811532 高雄市楠梓區卓越路2號<br />\n\t電話：07-6011000</li>\n\t<li>建工校區 807618&nbsp;高雄市三民區建工路415號<br />\n\t燕巢校區 824004 高雄市燕巢區深中路58號<br />\n\t電話：07-3814526</li>\n\t<li>楠梓校區 811213 高雄市楠梓區海專路142號<br />\n\t電話：07-3617141<br />\n\t旗津校區 805301 高雄市旗津區中洲三路482號<br />\n\t電話：07-8100888</li>\n</ul>\n<!--<h style=\" font-size:0em; color:rgba(0,0,0,0); opacity:0; filter:alpha(opacity=0); margin:0;\">&nbsp;</h></div>-->\n\n<div style=\"text-align: center\">\n<p><h>校安中心24小時緊急聯絡專線</h><br />\n0800-550-995</p>\n</div>\n\n<div class=\"bt_second\">\n<ul>\n\t<li><a href=\"https://www.nkust.edu.tw/var/file/0/1000/img/75/100151945.pdf\" target=\"_blank\" title=\"【開啟PDF檔】行政單位聯絡窗口(另開新視窗)\">行政單位聯絡窗口</a>|</li>\n\t<li><a href=\"https://www.nkust.edu.tw/p/412-1000-1920.php\" title=\"交通資訊\">交通資訊</a>|</li>\n\t<!--<li><a href=\"https://www.nkust.edu.tw/p/412-1000-1921.php\"  title=\"校園導覽\">校園導覽</a>|</li>-->\n\t<li><a href=\"https://www.nkust.edu.tw/p/412-1000-2797.php\" title=\"高科大散步地圖\">高科大散步地圖</a>|</li>\n\t<li><a href=\"https://www.nkust.edu.tw/p/404-1000-4421.php\" title=\"隱私保護聲明\">隱私保護聲明</a>|</li>\n</ul>\n&nbsp;\n\n<ul>\n\t<li><a href=\"https://www.youtube.com/channel/UCk7QGAi2QAFrH63mPPX-apw/\" target=\"_blank\" title=\"高科大youtube(另開新視窗)\"><img alt=\"高科大youtube\" height=\"32\" src=\"/var/file/0/1000/img/2/iconfinder_youtube_circle_294712.png\" style=\"border-width: 0px; border-style: solid;\" width=\"32\" /></a></li>\n\t<li><a href=\"https://www.facebook.com/NKUST2018\" target=\"_blank\" title=\"高科大FB(另開新視窗)\"><img alt=\"高科大FB\" height=\"32\" src=\"/var/file/0/1000/img/2/iconfinder_Facebook-icon_380455.png\" style=\"border-width: 0px; border-style: solid;\" width=\"32\" /></a></li>\n\t<li><a href=\"https://www.instagram.com/nkust4u/\" target=\"_blank\" title=\"高科大youtube(另開新視窗)\"><img alt=\"高科大IG\" height=\"32\" src=\"/var/file/0/1000/img/2/IG.png\" style=\"border-width: 0px; border-style: solid;\" width=\"32\" /></a></li>\n\t<li><a href=\"https://www.linkedin.com/company/82840828/admin\" target=\"_blank\" title=\"高科大FB(另開新視窗)\"><img alt=\"高科大LinkedIn\" height=\"32\" src=\"/var/file/0/1000/img/2/LinkedIn.png\" style=\"border-width: 0px; border-style: solid;\" width=\"32\" /></a></li>\n\t<li><a href=\"https://accessibility.moda.gov.tw/Applications/Detail?category=20210823115656\" target=\"_blank\" title=\"無障礙網站\"><img alt=\"通過AA檢測等級無障礙網頁檢測\" height=\"31\" src=\"https://accessibility.moda.gov.tw/ImagesUploads/05bfd164-030e-448f-b83b-37c7dcb01eec.jpg\" style=\"border-width: 0px; border-style: solid;\" title=\"通過AA檢測等級無障礙網頁檢測_另開視窗\" width=\"88\" /> </a></li>\n</ul>\n</div>\n\n<div style=\"text-align: center\">\n<p>Copyright &copy; 2018 國立高雄科技大學 NKUST</p>\n</div>\n\n<p>&nbsp;</p>\n<style type=\"text/css\">.owl-carousel .owl-dots {\n    text-align: right;\n}\n.owl-carousel .owl-dots .owl-dot{\nfloat:none;\n}\n.module-rss .mdate.before {\n    margin-left: 15px;\n}\n.module-rss .mdate:before {\n    content: \"活動日期：\";\n}\n.module-rss .v-td .d-txt {\n    display: flex;\n    flex-direction: column-reverse;\n}\nheader.mt.mt-subhead {\nbackground: #D1A43F;\n    display: block;\n    padding: 10px 0 20px;\n    font-size: 1.8rem;\n    margin: 0;\n}\n.module-rss header.mt.mt-subhead {\n    background: #374C8F;\n    //background: #4d2aa1;\n}\n.mt-subhead > * {\n    display: block;\n    margin-top: 0;\n    margin-bottom: 0;\n    color: #fff;\n    text-align: center;\n    line-height: 15px;\n}\n.dropdown-toggle:focus {\n    outline: 5px auto -webkit-focus-ring-color;\n}\n.d-title .d-txt > h5 {\n    position: relative;\n    z-index: 2;\n    padding: 5px;\n    text-align: left;\n    white-space: nowrap;\n    text-overflow: ellipsis;\n}\n.row_1 div.col_02 .module-special .d-title h5 {\n    margin: 0;\n    white-space: nowrap;\n    text-overflow: ellipsis;\n}\n\n.module .d-title .d-txt h5, .module-special .d-title .d-txt h5 {\n    display: block;\n}\n\n.d-txt > h5 {\n    font-size: 1.0em;\n    line-height: 1.5em;\n    /*text-align: center;*/\n}\n.row_0 .module-special h5 {\n    padding-left: 16px;\n    position: relative;\n    text-align: left;\n}\n\n.page_mobilehome .row_1 div.col_03 .module-special {\n    padding: .2em 2.5em .5em;\n    background: url(/var/file/0/1000/mobilestyle/485/images/mo_bg.jpg) no-repeat center;\n    background-size: cover;\n    padding-top: 1.2em;\n}\n\n//NEW\n.more {}\n\n.row_0 .module-special .mb .more {\n    position: relative;\n    top: 0px;\n    right: 0;\n    z-index: 999;\n}\n\n\n.minner .mt .mt-title {\n    background: #374C8F;\n}\n.mouter .mt .mt-title {\n    background: #D1A43F;\n}\n.M18925 .md_style99 .minner .mt .mt-title {\n    background: #a12a46;\n}\n.row_0 .col_02 { //首頁的底色變色\n    //width: 65%;\n    //background: #6b679f30;\n}\n\n\n.mtitle {\n    position: relative;\n    z-index: 2;\n    padding: 5px;\n    border-bottom: 1px solid #d6d6d6;\n}\n.M18918  .module .minner .mb {//最新消息 背景色 灰\n    padding-top: 1em;\n    background-color: #eaeae6;\n}\n.M18922  .module .minner .mb {//遠見 背景色 灰\n    padding-top: 1em;\n    background-color: #eaeae6;\n}\n\n\n.row_0 {     \n    background: url(https://cc.nkust.edu.tw/var/file/25/1025/img/412/2022-01-20_102942.png);\n}\n.row_1 {     \n    background: url(https://cc.nkust.edu.tw/var/file/25/1025/img/412/2022-01-20_102942.png);\n}\n.row_0 .container {\nbackground: #fff;\n    box-shadow: 0px 0 10px 0px rgb(0 0 0/ 40%);\n    border-bottom: 4px solid #314589; \n\n}\n\n.row_0 .module-special .mtitle {\n    padding-left: 16px;\n    position: relative;\n    font-size: 1.2em;\n    font-weight: bold;\n}\n.mdetail {\n    text-align: left;\n    line-height: 26px;\n    margin-top: 0.5em;\n    font-size: 1.0em;\n}\n.mt .mt-title {\n    font-size: 1.3em;\n    color: #eee;\n    font-weight: bold;\n    text-align: center;\n    padding: 15px 0;\n}\n@media screen  and (max-width: 1200px){\n.mt .mt-title {\n    font-size: 1.1em;\n    color: #eee;\n    font-weight: bold;\n    text-align: center;\n    padding: 15px 0;\n    line-height: 20px;\n}\n}\n\n@media (min-width: 768px){\n.navbar-nav {\n    justify-items: center;\n    padding-left: 20%;\n    float: left;\n    margin: 0;\n}\n}\n</style>\n</div>\n\n\t\n</div>\n</div>\n\n\n\t<button class=\"toTop\" title=\"回到頂部\">\n    \t<span>回到頂部</span>\n\t</button>\n<script>\n\t// 返回頂部\n\t$(document).ready(function(){\n\t    gotop();\n\t}); \n\t$(window).scroll(function(){\n\t    gotop();\n\t});\n\t$('.toTop').click(function(){\n\t    $('html, body, .wrap').animate({scrollTop: '0px'}, 200);\n\t\t $(\".focusable\").focus();\n\t});\n\tfunction gotop(){\n\t    var  winH = $(window).height();\n\t    var  scroll = $(window).scrollTop();\n\t    if(scroll > 100 ){\n\t        $('.toTop').show();\n\t    }\n\t    else {\n\t        $('.toTop').hide();\n\t    }\n\t}\n\t</script>\n\n\n\n\n</div>\n</div>\n<!-- generated at Tue Sep 26 2023 15:09:42 --></div>\n\n\n</div>\n</div>\n<div class=\"fpbgvideo\"></div>\n\n\n\n\n<div id=\"_pop_login\" class=\"mpopdiv\">\n<script>$(document).ready(function() {$.hajaxOpenUrl('/app/index.php?Action=mobileloadmod&Type=mobilepoplogin&Nbr=0','#_pop_login','',function(){menuDropAct();});})</script>\n</div>\n\n\n<div id=\"_pop_tips\" class=\"mtips\">\n\t<div class=\"mbox\">\n\t</div>\n</div>\n<div id=\"_pop_dialog\" class=\"mdialog\">\n\t<div class=\"minner\">\n\t\t<div class=\"mcont\">\n\t\t</div>\n\t\t<footer class=\"mdialog-foot\">\n        \t<button type=\"submit\" class=\"mbtn mbtn-s\">OK</button>\n        \t<button type=\"submit\" class=\"mbtn mbtn-c\">Cancel</button>\n\t\t</footer>\n\t</div>\n</div>\n\n<!-- Global site tag (gtag.js) - Google Analytics -->\n<script async src=\"https://www.googletagmanager.com/gtag/js?id=UA-142388825-3\"></script>\n<script>\n  window.dataLayer = window.dataLayer || [];\n  function gtag(){dataLayer.push(arguments);}\n  gtag('js', new Date());\n\n  gtag('config', 'UA-142388825-3');\n</script>\n<!-- Global site tag (gtag.js) - Google Ads: 619207031 -->\n<script async src=\"https://www.googletagmanager.com/gtag/js?id=AW-619207031\"></script>\n<script>\n  window.dataLayer = window.dataLayer || [];\n  function gtag(){dataLayer.push(arguments);}\n  gtag('js', new Date());\n\n  gtag('config', 'AW-619207031');\n</script>\n<script async src=\"https://www.googletagmanager.com/gtag/js?id=UA-142388825-1\"></script>\n<script>\n  window.dataLayer = window.dataLayer || [];\n  function gtag(){dataLayer.push(arguments);}\n  gtag('js', new Date());\n\n  gtag('config', 'UA-142388825-1');\n</script>\n<!--<script>NProgress.done();</script>-->\n<script>\nfunction popChkLogin(){\n\tif(typeof(loginStat)=='undefined') {\n   \tvar chkstat=0;\n   \tvar chkUrl='/app/index.php?Action=mobilelogin&Op=chklogin';\n   \tvar chkData = [];\n   \tvar chkObj=$.hajaxReturn(chkUrl,chkData);\n   \tchkstat=chkObj.stat;\n\t\tif(chkstat) {\n\t\t\tloginStat=\"login\"; \n\t\t\treturn true;\n\t\t}else {\n\t\t\tloginStat=\"logout\"; \n\t\t\treturn false;\n\t\t}\t\n\t}else {\n\t\tif(loginStat==\"login\") return true;\n\t\telse return false;\n\t}\n}\n\n$(document).ready(function(){\n   $('head').append(\"<style>@media (min-width: 481px) {.row_0 .col_01 { width: 0%;}.row_0 .col_02 { width: 65%;}.row_0 .col_03 { width: 35%;}}@media (min-width: 481px) {.row_1 .col_01 { width: 0%;}.row_1 .col_02 { width: 65%;}.row_1 .col_03 { width: 35%;}}@media (min-width: 481px) {.row_2 .col_01 { width: 0%;}.row_2 .col_02 { width: 100%;}.row_2 .col_03 { width: 0%;}}@media (min-width: 481px) {.row_3 .col_01 { width: 0%;}.row_3 .col_02 { width: 100%;}.row_3 .col_03 { width: 0%;}}@media (min-width: 481px) {.row_4 .col_01 { width: 0%;}.row_4 .col_02 { width: 100%;}.row_4 .col_03 { width: 0%;}}</style>\");\n});\n\n</script>\n</body>\n</html>\n<!-- generated at Wed Oct 25 2023 11:49:41 -->"
}